{
  "fetchedAt": "2026-05-09T00:00:00.000Z",
  "weekNo": 19,
  "weekStart": "2026-05-03",
  "store": "rema1000",
  "productCount": 36,
  "campaignCount": 34,
  "note": "Initial seed snapshot — will be replaced by the daily GitHub Actions refresh.",
  "products": [
    {"id":101394,"n":"OAT BARISTA HAVREDRIK","u":"1 LTR. / NATURLI'","d":"Drikkevarer","c":"Plantedrikke","p":10,"np":18.15,"cu":"ltr","cup":10,"e":"2026-05-09","s":"2026-05-03","camp":1,"img":"https://rema-product-images.digital.rema1000.dk/101394/1-medium-vVoryaKJP3.webp"},
    {"id":108618,"n":"HAVREDRIK","u":"1 LTR. / NATURLI'","d":"Drikkevarer","c":"Plantedrikke","p":10,"np":23.15,"cu":"ltr","cup":10,"e":"2026-05-09","s":"2026-05-03","camp":1,"img":"https://rema-product-images.digital.rema1000.dk/108618/1-medium-2B943DWGqk.webp"},
    {"id":304020,"n":"ØKO. BANANER FAIRTRADE","u":"1 BDT. / FAIRTRADE","d":"Frugt & grønt","c":"Pære, æble, banan & citrusfrugt","p":8,"np":10,"cu":"bdt","cup":8,"e":"2026-05-09","s":"2026-05-03","camp":1,"img":"https://rema-product-images.digital.rema1000.dk/304020/1-medium-AKqexlbnop.webp"},
    {"id":304766,"n":"PINK LADY ÆBLER","u":"1 BAKKE","d":"Frugt & grønt","c":"Pære, æble, banan & citrusfrugt","p":15,"np":27,"cu":"bakke","cup":15,"e":"2026-05-09","s":"2026-05-03","camp":1,"img":"https://rema-product-images.digital.rema1000.dk/304766/1-medium-pyoza6MAPX.webp"},
    {"id":110144,"n":"DIJON SENNEP","u":"380 GR. / MAILLE","d":"Kolonial","c":"Ketchup, remoulade, mayonnaise","p":18,"np":null,"cu":"kg","cup":47.37,"e":"2026-07-22","s":"2026-05-03","camp":0,"img":"https://rema-product-images.digital.rema1000.dk/110144/1-medium-xePwydVdqw.webp"},
    {"id":110160,"n":"GRAASTEN SENNEP","u":"800 GR.","d":"Kolonial","c":"Ketchup, remoulade, mayonnaise","p":18,"np":null,"cu":"kg","cup":22.5,"e":"2026-05-09","s":"2026-05-03","camp":1,"img":"https://rema-product-images.digital.rema1000.dk/110160/1-medium-6xqAzRkE9D.webp"},
    {"id":110633,"n":"HELLMANN'S REAL MAYO","u":"430 ML.","d":"Kolonial","c":"Ketchup, remoulade, mayonnaise","p":18,"np":null,"cu":"ltr","cup":41.86,"e":"2026-06-10","s":"2026-05-03","camp":0,"img":"https://rema-product-images.digital.rema1000.dk/110633/1-medium-YLPjLWmVqk.webp"},
    {"id":118421,"n":"EKS. JOMFRU OLIVENOLIE","u":"500 ML. / FARCHIONI","d":"Kolonial","c":"Olie, eddike & balsamico","p":35,"np":51.04,"cu":"ltr","cup":70,"e":"2026-05-09","s":"2026-05-07","camp":1,"img":"https://rema-product-images.digital.rema1000.dk/118421/1-medium-bJ9YaZbZ9L.webp"},
    {"id":119092,"n":"GRAASTEN KETCHUP","u":"800 GR.","d":"Kolonial","c":"Ketchup, remoulade, mayonnaise","p":18,"np":null,"cu":"kg","cup":22.5,"e":"2026-05-09","s":"2026-05-03","camp":1,"img":"https://rema-product-images.digital.rema1000.dk/119092/1-medium-OJq52xbl9p.webp"},
    {"id":180056,"n":"HAVREGRYN GROVVALSEDE","u":"1 KG. / REMA 1000","d":"Kolonial","c":"Morgenmad","p":5,"np":7.95,"cu":"kg","cup":5,"e":"2026-05-09","s":"2026-05-03","camp":1,"img":"https://rema-product-images.digital.rema1000.dk/180056/1-medium-18oXwgyJPk.webp"},
    {"id":180122,"n":"HAVREGRYN FINVALSEDE","u":"1 KG. / REMA 1000","d":"Kolonial","c":"Morgenmad","p":5,"np":7.95,"cu":"kg","cup":5,"e":"2026-05-09","s":"2026-05-03","camp":1,"img":"https://rema-product-images.digital.rema1000.dk/180122/1-medium-pyozpJdk9X.webp"},
    {"id":400001,"n":"GRILLKOTELETTER M. TOMAT","u":"300 GR. / DANSK","d":"Kød, fisk & fjerkræ","c":"Gris","p":29,"np":32.95,"cu":"kg","cup":96.67,"e":"2026-05-09","s":"2026-05-03","camp":1,"img":"https://rema-product-images.digital.rema1000.dk/400001/1-medium-ElPBrmGWPk.webp"},
    {"id":400002,"n":"KOTELETTER M. HVIDLØG","u":"300 GR. / DANSK","d":"Kød, fisk & fjerkræ","c":"Gris","p":29,"np":32.95,"cu":"kg","cup":96.67,"e":"2026-05-09","s":"2026-05-03","camp":1,"img":"https://rema-product-images.digital.rema1000.dk/400002/1-medium-kAonrE0box.webp"},
    {"id":400043,"n":"NAKKEKOTELETTER M. SMOKEY BBQ","u":"300 GR. / DANSK","d":"Kød, fisk & fjerkræ","c":"Gris","p":29,"np":32.95,"cu":"kg","cup":96.67,"e":"2026-05-09","s":"2026-05-03","camp":1,"img":"https://rema-product-images.digital.rema1000.dk/400043/1-medium-dyomVk3BqV.webp"},
    {"id":400466,"n":"HAKKET OKSEKØD 8-12%","u":"400 GR. / REMA 1000","d":"Kød, fisk & fjerkræ","c":"Hakket kød","p":25,"np":29.95,"cu":"kg","cup":62.5,"e":"2026-05-09","s":"2026-05-03","camp":1,"img":"https://rema-product-images.digital.rema1000.dk/400466/1-medium-pyozbk2AoX.webp"},
    {"id":400552,"n":"HAKKET GRIS & KALV 8-12%","u":"500 GR. / DANSK","d":"Kød, fisk & fjerkræ","c":"Hakket kød","p":25,"np":29.95,"cu":"kg","cup":50,"e":"2026-05-09","s":"2026-05-03","camp":1,"img":"https://rema-product-images.digital.rema1000.dk/400552/1-medium-NpP70z1XoO.webp"},
    {"id":400615,"n":"FLÆSKESTEG OVNKLAR","u":"1.45 KG. / DANSK","d":"Kød, fisk & fjerkræ","c":"Gris","p":49.16,"np":115.86,"cu":"kg","cup":33.9,"e":"2026-05-09","s":"2026-05-03","camp":1,"img":"https://rema-product-images.digital.rema1000.dk/400615/1-medium-KpqRB6DbqL.webp"},
    {"id":404933,"n":"CRISPY LÅRFILET","u":"350 GR. / REMA 1000","d":"Kød, fisk & fjerkræ","c":"Kylling","p":29,"np":34.95,"cu":"kg","cup":82.86,"e":"2026-05-09","s":"2026-05-03","camp":1,"img":"https://rema-product-images.digital.rema1000.dk/404933/1-medium-YLPjy60L9k.webp"},
    {"id":404954,"n":"KYLLINGEBRYST M. BBQ","u":"325 GR. / DANSK","d":"Kød, fisk & fjerkræ","c":"Kylling","p":29,"np":32.95,"cu":"kg","cup":89.23,"e":"2026-05-09","s":"2026-05-03","camp":1,"img":"https://rema-product-images.digital.rema1000.dk/404954/1-medium-Al90zOK7o8.webp"},
    {"id":404961,"n":"KYLLINGELÅR M. BBQ","u":"800 GR. / DANSK","d":"Kød, fisk & fjerkræ","c":"Kylling","p":29,"np":32.95,"cu":"kg","cup":36.25,"e":"2026-05-09","s":"2026-05-03","camp":1,"img":"https://rema-product-images.digital.rema1000.dk/404961/1-medium-Z8qp71N0o3.webp"},
    {"id":404966,"n":"KYLLINGELÅR M. HAVSALT & PEBER","u":"825 GR. / DANSK","d":"Kød, fisk & fjerkræ","c":"Kylling","p":29,"np":32.95,"cu":"kg","cup":35.15,"e":"2026-05-09","s":"2026-05-03","camp":1,"img":"https://rema-product-images.digital.rema1000.dk/404966/1-medium-pyozbn8LoX.webp"},
    {"id":404994,"n":"KYLLINGEINDERFILET","u":"300 GR. / DANSK","d":"Kød, fisk & fjerkræ","c":"Kylling","p":29,"np":32.95,"cu":"kg","cup":96.67,"e":"2026-05-09","s":"2026-05-03","camp":1,"img":"https://rema-product-images.digital.rema1000.dk/404994/1-medium-vVor0OaJ93.webp"},
    {"id":404995,"n":"KYLLINGEBRYSTFILET","u":"450 GR. / DANSK","d":"Kød, fisk & fjerkræ","c":"Kylling","p":29,"np":34.95,"cu":"kg","cup":64.44,"e":"2026-05-09","s":"2026-05-03","camp":1,"img":"https://rema-product-images.digital.rema1000.dk/404995/1-medium-v09glA8DPA.webp"},
    {"id":20152,"n":"MADFLØDE 13%","u":"300 ML. / ARLA LACTOFREE","d":"Mejeri","c":"Fløde m.v.","p":10,"np":15.95,"cu":"ltr","cup":33.33,"e":"2026-05-09","s":"2026-05-03","camp":1,"img":"https://rema-product-images.digital.rema1000.dk/20152/1-medium-NpP7A7EqOl.webp"},
    {"id":20252,"n":"CHEASY SKYR SKOVBÆR","u":"1000 GR.","d":"Mejeri","c":"Yoghurt m.v.","p":20,"np":28.95,"cu":"kg","cup":20,"e":"2026-05-09","s":"2026-05-03","camp":1,"img":"https://rema-product-images.digital.rema1000.dk/20252/1-medium-NpP7AX2qOl.webp"},
    {"id":21810,"n":"PISKEFLØDE 36%","u":"250 ML. / ARLA LACTOFREE","d":"Mejeri","c":"Fløde m.v.","p":10,"np":16.5,"cu":"ltr","cup":40,"e":"2026-05-09","s":"2026-05-03","camp":1,"img":"https://rema-product-images.digital.rema1000.dk/21810/1-medium-Al90aaRP8w.webp"},
    {"id":21937,"n":"FRAICHE 13%","u":"200 GR. / ARLA LACTOFREE","d":"Mejeri","c":"Syrnede produkter","p":10,"np":12.5,"cu":"kg","cup":50,"e":"2026-05-09","s":"2026-05-03","camp":1,"img":"https://rema-product-images.digital.rema1000.dk/21937/1-medium-JzPJlMYqkb.webp"},
    {"id":22393,"n":"NATUREL YOGHURT","u":"1000 GR. / ARLA LACTOFREE","d":"Mejeri","c":"Yoghurt m.v.","p":10,"np":19.74,"cu":"kg","cup":10,"e":"2026-05-09","s":"2026-05-03","camp":1,"img":"https://rema-product-images.digital.rema1000.dk/22393/1-medium-xQq848zqZd.webp"},
    {"id":22394,"n":"YOGHURT PÆRE/BANAN","u":"1000 GR. / ARLA LACTOFREE","d":"Mejeri","c":"Yoghurt m.v.","p":10,"np":22.19,"cu":"kg","cup":10,"e":"2026-05-09","s":"2026-05-03","camp":1,"img":"https://rema-product-images.digital.rema1000.dk/22394/1-medium-vVorxRp93z.webp"},
    {"id":24015,"n":"CHEASY SKYR VANILJE","u":"1000 GR.","d":"Mejeri","c":"Yoghurt m.v.","p":20,"np":28.95,"cu":"kg","cup":20,"e":"2026-05-09","s":"2026-05-03","camp":1,"img":"https://rema-product-images.digital.rema1000.dk/24015/1-medium-KpqRlZdPLz.webp"},
    {"id":24017,"n":"CHEASY SKYR MANGO & LIME","u":"1000 GR.","d":"Mejeri","c":"Yoghurt m.v.","p":20,"np":28.95,"cu":"kg","cup":20,"e":"2026-05-09","s":"2026-05-03","camp":1,"img":"https://rema-product-images.digital.rema1000.dk/24017/1-medium-Z8qpEGY93N.webp"},
    {"id":24018,"n":"CHEASY SKYR PASSION & BANAN","u":"1000 GR.","d":"Mejeri","c":"Yoghurt m.v.","p":20,"np":28.95,"cu":"kg","cup":20,"e":"2026-05-09","s":"2026-05-03","camp":1,"img":"https://rema-product-images.digital.rema1000.dk/24018/1-medium-2B94DJr9kM.webp"},
    {"id":24235,"n":"YOGHURT SKOVBÆR","u":"1000 GR. / SKÅNEMEJERIER","d":"Mejeri","c":"Yoghurt m.v.","p":10,"np":20.13,"cu":"kg","cup":10,"e":"2026-05-09","s":"2026-05-03","camp":1,"img":"https://rema-product-images.digital.rema1000.dk/24235/1-medium-Gb9k2Bvq75.webp"},
    {"id":24236,"n":"YOGHURT TROPISK","u":"1000 GR. / SKÅNEMEJERIER","d":"Mejeri","c":"Yoghurt m.v.","p":10,"np":20.13,"cu":"kg","cup":10,"e":"2026-05-09","s":"2026-05-03","camp":1,"img":"https://rema-product-images.digital.rema1000.dk/24236/1-medium-7doLpvWo6r.webp"},
    {"id":25845,"n":"KÆRGÅRDEN SMØRBAR LET","u":"200 GR. / ARLA","d":"Mejeri","c":"Smør & fedtstoffer","p":12,"np":24.95,"cu":"kg","cup":60,"e":"2026-05-09","s":"2026-05-03","camp":1,"img":"https://rema-product-images.digital.rema1000.dk/25845/1-medium-ElPBn38PkG.webp"},
    {"id":25847,"n":"KÆRGÅRDEN SMØRBAR ORIGINAL","u":"200 GR. / ARLA","d":"Mejeri","c":"Smør & fedtstoffer","p":12,"np":18.95,"cu":"kg","cup":60,"e":"2026-05-09","s":"2026-05-03","camp":1,"img":"https://rema-product-images.digital.rema1000.dk/25847/1-medium-3MoMw4395E.webp"}
  ]
}
